Metadata-Version: 2.1
Name: CipherGuard
Version: 8.0
Summary: By @rrrrrf In telegram 
Author: Programmer Golden 
Classifier: Programming Language :: Python :: 3
Classifier: Operating System :: OS Independent
Classifier: License :: OSI Approved :: MIT License
License-File: LICENSE.txt
